kiri_ocr/__init__.py
kiri_ocr/cli.py
kiri_ocr/core.py
kiri_ocr/generator.py
kiri_ocr/model.py
kiri_ocr/renderer.py
kiri_ocr/training.py
kiri_ocr/detector/__init__.py
kiri_ocr/detector/base.py
kiri_ocr/detector/craft/__init__.py
kiri_ocr/detector/craft/dataset.py
kiri_ocr/detector/craft/imgproc.py
kiri_ocr/detector/craft/model.py
kiri_ocr/detector/craft/training.py
kiri_ocr/detector/craft/utils.py
kiri_ocr/detector/db/__init__.py
kiri_ocr/detector/db/model.py
kiri_ocr/detector/legacy/__init__.py
kiri_ocr/detector/legacy/detector.py
kiri_ocr-0.2.12.dist-info/licenses/LICENSE
kiri_ocr-0.2.12.dist-info/METADATA
kiri_ocr-0.2.12.dist-info/WHEEL
kiri_ocr-0.2.12.dist-info/entry_points.txt
kiri_ocr-0.2.12.dist-info/top_level.txt
kiri_ocr-0.2.12.dist-info/RECORD
