Metadata-Version: 2.4
Name: kiri_ocr
Version: 0.2.12
Summary: A lightweight OCR library for Khmer and English documents
Author-email: Tmob <mrrtmob@gmail.com>
License: Apache-2.0
Project-URL: Homepage, https://github.com/mrrtmob/kiri-ocr
Project-URL: Repository, https://github.com/mrrtmob/kiri-ocr
Project-URL: Issues, https://github.com/mrrtmob/kiri-ocr/issues
Project-URL: Documentation, https://github.com/mrrtmob/kiri-ocr/wiki
Keywords: ocr,khmer,english,deep-learning,pytorch,computer-vision
Classifier: Development Status :: 4 - Beta
Classifier: Intended Audience :: Developers
Classifier: License :: OSI Approved :: Apache Software License
Classifier: Programming Language :: Python :: 3
Classifier: Programming Language :: Python :: 3.6
Classifier: Programming Language :: Python :: 3.7
Classifier: Programming Language :: Python :: 3.8
Classifier: Programming Language :: Python :: 3.9
Classifier: Programming Language :: Python :: 3.10
Classifier: Programming Language :: Python :: 3.11
Classifier: Operating System :: OS Independent
Classifier: Topic :: Scientific/Engineering :: Artificial Intelligence
Classifier: Topic :: Text Processing :: Linguistic
Requires-Python: >=3.6
License-File: LICENSE
Requires-Dist: torch>=2.0.0
Requires-Dist: torchvision>=0.15.0
Requires-Dist: numpy>=1.24.0
Requires-Dist: opencv-python>=4.7.0
Requires-Dist: Pillow>=9.0.0
Requires-Dist: tqdm>=4.65.0
Requires-Dist: matplotlib>=3.7.0
Requires-Dist: datasets>=2.14.0
Requires-Dist: huggingface_hub>=0.16.0
Requires-Dist: PyYAML
Requires-Dist: safetensors>=0.4.0
Requires-Dist: onnxruntime-gpu>=1.15.0
Requires-Dist: pyclipper>=1.3.0
Requires-Dist: shapely>=2.0.0
Dynamic: license-file
